silly_db/__init__.py
silly_db/__main__.py
silly_db/cmd.py
silly_db/db.py
silly_db/exceptions.py
silly_db/helpers.py
silly_db/selections.py
silly_db/models/__init__.py
silly_db/models/silly_model.py
silly_db/plop/__init__.py
silly_db/plop/__main__.py
silly_db/plop/db/main_example.py
silly_db/plop/db/database/migrations/00_initial.sql
silly_db/plop/db/database/migrations/01_populate.sql
silly_db/plop/db/database/migrations/migrations.txt
silly_db-2.0.2.dist-info/LICENSE.md
silly_db-2.0.2.dist-info/METADATA
silly_db-2.0.2.dist-info/WHEEL
silly_db-2.0.2.dist-info/entry_points.txt
silly_db-2.0.2.dist-info/top_level.txt
silly_db-2.0.2.dist-info/RECORD
