Metadata-Version: 2.1
Name: silly-db
Version: 2.0.2
Summary: Very light ORM for SQLite, simple and efficient
Home-page: https://github.com/byoso/silly_db
Author: Vincent Fabre
Author-email: peigne.plume@gmail.com
License: MIT
Keywords: database sqlite3 sqlite db orm
Platform: UNKNOWN
Classifier: License :: OSI Approved :: MIT License
Classifier: Programming Language :: Python :: 3
Classifier: Development Status :: 5 - Production/Stable
Classifier: License :: OSI Approved :: MIT License
Classifier: Natural Language :: English
Classifier: Topic :: Software Development :: Libraries :: Application Frameworks
Requires-Python: >=3.6
License-File: LICENSE.md
Requires-Dist: flamewok (>=1.1.0)
